{
  "edges": [
    {
      "bin_idx": 1,
      "count": 15,
      "dst": "proc:container:0a68610a418d:pid:167116",
      "event_name": "mmap",
      "event_names": [
        "mmap"
      ],
      "first_ts": 37651521908000,
      "last_ts": 37653083022000,
      "segments": [
        {
          "bin": 1,
          "count": 15
        }
      ],
      "src": "file:fd:-1_container:0a68610a418d_pid:167116",
      "type": "Mmap"
    },
    {
      "bin_idx": 2,
      "count": 6,
      "dst": "proc:container:0a68610a418d:pid:167116",
      "event_name": "mmap",
      "event_names": [
        "mmap"
      ],
      "first_ts": 37653954480000,
      "last_ts": 37655288541000,
      "segments": [
        {
          "bin": 2,
          "count": 6
        }
      ],
      "src": "file:fd:-1_container:0a68610a418d_pid:167116",
      "type": "Mmap"
    },
    {
      "bin_idx": 3,
      "count": 9,
      "dst": "proc:container:0a68610a418d:pid:167116",
      "event_name": "mmap",
      "event_names": [
        "mmap"
      ],
      "first_ts": 37655569841000,
      "last_ts": 37656831461000,
      "segments": [
        {
          "bin": 3,
          "count": 9
        }
      ],
      "src": "file:fd:-1_container:0a68610a418d_pid:167116",
      "type": "Mmap"
    },
    {
      "bin_idx": 4,
      "count": 6,
      "dst": "proc:container:0a68610a418d:pid:167116",
      "event_name": "mmap",
      "event_names": [
        "mmap"
      ],
      "first_ts": 37658485731000,
      "last_ts": 37659368648000,
      "segments": [
        {
          "bin": 4,
          "count": 6
        }
      ],
      "src": "file:fd:-1_container:0a68610a418d_pid:167116",
      "type": "Mmap"
    },
    {
      "bin_idx": 5,
      "count": 3,
      "dst": "proc:container:0a68610a418d:pid:167116",
      "event_name": "mmap",
      "event_names": [
        "mmap"
      ],
      "first_ts": 37659682567000,
      "last_ts": 37659682669000,
      "segments": [
        {
          "bin": 5,
          "count": 3
        }
      ],
      "src": "file:fd:-1_container:0a68610a418d_pid:167116",
      "type": "Mmap"
    },
    {
      "bin_idx": 6,
      "count": 6,
      "dst": "proc:container:0a68610a418d:pid:167116",
      "event_name": "mmap",
      "event_names": [
        "mmap"
      ],
      "first_ts": 37662055698000,
      "last_ts": 37663161973000,
      "segments": [
        {
          "bin": 6,
          "count": 6
        }
      ],
      "src": "file:fd:-1_container:0a68610a418d_pid:167116",
      "type": "Mmap"
    },
    {
      "bin_idx": 8,
      "count": 15,
      "dst": "proc:container:0a68610a418d:pid:167116",
      "event_name": "mmap",
      "event_names": [
        "mmap"
      ],
      "first_ts": 37666178097000,
      "last_ts": 37667155043000,
      "segments": [
        {
          "bin": 8,
          "count": 15
        }
      ],
      "src": "file:fd:-1_container:0a68610a418d_pid:167116",
      "type": "Mmap"
    },
    {
      "bin_idx": 9,
      "count": 3,
      "dst": "proc:container:0a68610a418d:pid:167116",
      "event_name": "mmap",
      "event_names": [
        "mmap"
      ],
      "first_ts": 37667541916000,
      "last_ts": 37667542239000,
      "segments": [
        {
          "bin": 9,
          "count": 3
        }
      ],
      "src": "file:fd:-1_container:0a68610a418d_pid:167116",
      "type": "Mmap"
    },
    {
      "bin_idx": 10,
      "count": 9,
      "dst": "proc:container:0a68610a418d:pid:167116",
      "event_name": "mmap",
      "event_names": [
        "mmap"
      ],
      "first_ts": 37669612831000,
      "last_ts": 37670881220000,
      "segments": [
        {
          "bin": 10,
          "count": 9
        }
      ],
      "src": "file:fd:-1_container:0a68610a418d_pid:167116",
      "type": "Mmap"
    },
    {
      "bin_idx": 11,
      "count": 3,
      "dst": "proc:container:0a68610a418d:pid:167116",
      "event_name": "mmap",
      "event_names": [
        "mmap"
      ],
      "first_ts": 37672054378000,
      "last_ts": 37672054739000,
      "segments": [
        {
          "bin": 11,
          "count": 3
        }
      ],
      "src": "file:fd:-1_container:0a68610a418d_pid:167116",
      "type": "Mmap"
    },
    {
      "bin_idx": 12,
      "count": 9,
      "dst": "proc:container:0a68610a418d:pid:167116",
      "event_name": "mmap",
      "event_names": [
        "mmap"
      ],
      "first_ts": 37673782214000,
      "last_ts": 37675402075000,
      "segments": [
        {
          "bin": 12,
          "count": 9
        }
      ],
      "src": "file:fd:-1_container:0a68610a418d_pid:167116",
      "type": "Mmap"
    },
    {
      "bin_idx": 13,
      "count": 6,
      "dst": "proc:container:0a68610a418d:pid:167116",
      "event_name": "mmap",
      "event_names": [
        "mmap"
      ],
      "first_ts": 37676208808000,
      "last_ts": 37676235247000,
      "segments": [
        {
          "bin": 13,
          "count": 6
        }
      ],
      "src": "file:fd:-1_container:0a68610a418d_pid:167116",
      "type": "Mmap"
    },
    {
      "bin_idx": 14,
      "count": 12,
      "dst": "proc:container:0a68610a418d:pid:167116",
      "event_name": "mmap",
      "event_names": [
        "mmap"
      ],
      "first_ts": 37677980958000,
      "last_ts": 37679245851000,
      "segments": [
        {
          "bin": 14,
          "count": 12
        }
      ],
      "src": "file:fd:-1_container:0a68610a418d_pid:167116",
      "type": "Mmap"
    },
    {
      "bin_idx": 15,
      "count": 3,
      "dst": "proc:container:0a68610a418d:pid:167116",
      "event_name": "mmap",
      "event_names": [
        "mmap"
      ],
      "first_ts": 37680951564000,
      "last_ts": 37680951836000,
      "segments": [
        {
          "bin": 15,
          "count": 3
        }
      ],
      "src": "file:fd:-1_container:0a68610a418d_pid:167116",
      "type": "Mmap"
    }
  ],
  "metadata": {
    "reduction_config": {
      "edge_key_mode": "event_time_bin",
      "time_bin_seconds": 2,
      "window_seconds": 30
    }
  },
  "nodes": [
    {
      "id": "file:fd:-1_container:0a68610a418d_pid:167116",
      "meta": {
        "name": "fd:-1_container:0a68610a418d_pid:167116",
        "pathname": "fd:-1_container:0a68610a418d_pid:167116",
        "uuid": "fd:-1_container:0a68610a418d_pid:167116"
      }
    },
    {
      "id": "proc:container:0a68610a418d:pid:167116",
      "meta": {
        "container_id": "0a68610a418d",
        "container_image": "deploy-vuln-app:",
        "name": "python",
        "pathname": "",
        "pid": 167116,
        "pod_name": null,
        "uuid": "container:0a68610a418d:pid:167116"
      }
    }
  ]
}