{
  "edges": [
    {
      "bin_idx": 1,
      "count": 6,
      "dst": "proc:container:9f89600d11c0:pid:203736",
      "event_name": "mmap",
      "event_names": [
        "mmap"
      ],
      "first_ts": 40461178456000,
      "last_ts": 40462346218000,
      "segments": [
        {
          "bin": 1,
          "count": 6
        }
      ],
      "src": "file:fd:-1_container:9f89600d11c0_pid:203736",
      "type": "Mmap"
    },
    {
      "bin_idx": 3,
      "count": 6,
      "dst": "proc:container:9f89600d11c0:pid:203736",
      "event_name": "mmap",
      "event_names": [
        "mmap"
      ],
      "first_ts": 40465883487000,
      "last_ts": 40466812062000,
      "segments": [
        {
          "bin": 3,
          "count": 6
        }
      ],
      "src": "file:fd:-1_container:9f89600d11c0_pid:203736",
      "type": "Mmap"
    },
    {
      "bin_idx": 5,
      "count": 6,
      "dst": "proc:container:9f89600d11c0:pid:203736",
      "event_name": "mmap",
      "event_names": [
        "mmap"
      ],
      "first_ts": 40470153148000,
      "last_ts": 40470727985000,
      "segments": [
        {
          "bin": 5,
          "count": 6
        }
      ],
      "src": "file:fd:-1_container:9f89600d11c0_pid:203736",
      "type": "Mmap"
    },
    {
      "bin_idx": 7,
      "count": 6,
      "dst": "proc:container:9f89600d11c0:pid:203736",
      "event_name": "mmap",
      "event_names": [
        "mmap"
      ],
      "first_ts": 40474258770000,
      "last_ts": 40474975644000,
      "segments": [
        {
          "bin": 7,
          "count": 6
        }
      ],
      "src": "file:fd:-1_container:9f89600d11c0_pid:203736",
      "type": "Mmap"
    },
    {
      "bin_idx": 8,
      "count": 11,
      "dst": "proc:container:9f89600d11c0:pid:203736",
      "event_name": "mmap",
      "event_names": [
        "mmap"
      ],
      "first_ts": 40475641358000,
      "last_ts": 40475801281000,
      "segments": [
        {
          "bin": 8,
          "count": 11
        }
      ],
      "src": "file:fd:-1_container:9f89600d11c0_pid:203736",
      "type": "Mmap"
    },
    {
      "bin_idx": 13,
      "count": 6,
      "dst": "proc:container:9f89600d11c0:pid:203736",
      "event_name": "mmap",
      "event_names": [
        "mmap"
      ],
      "first_ts": 40485401061000,
      "last_ts": 40487046617000,
      "segments": [
        {
          "bin": 13,
          "count": 6
        }
      ],
      "src": "file:fd:-1_container:9f89600d11c0_pid:203736",
      "type": "Mmap"
    },
    {
      "bin_idx": 14,
      "count": 3,
      "dst": "proc:container:9f89600d11c0:pid:203736",
      "event_name": "mmap",
      "event_names": [
        "mmap"
      ],
      "first_ts": 40488051346000,
      "last_ts": 40488051500000,
      "segments": [
        {
          "bin": 14,
          "count": 3
        }
      ],
      "src": "file:fd:-1_container:9f89600d11c0_pid:203736",
      "type": "Mmap"
    },
    {
      "bin_idx": 15,
      "count": 3,
      "dst": "proc:container:9f89600d11c0:pid:203736",
      "event_name": "mmap",
      "event_names": [
        "mmap"
      ],
      "first_ts": 40490317758000,
      "last_ts": 40490317871000,
      "segments": [
        {
          "bin": 15,
          "count": 3
        }
      ],
      "src": "file:fd:-1_container:9f89600d11c0_pid:203736",
      "type": "Mmap"
    }
  ],
  "metadata": {
    "reduction_config": {
      "edge_key_mode": "event_time_bin",
      "time_bin_seconds": 2,
      "window_seconds": 30
    }
  },
  "nodes": [
    {
      "id": "file:fd:-1_container:9f89600d11c0_pid:203736",
      "meta": {
        "name": "fd:-1_container:9f89600d11c0_pid:203736",
        "pathname": "fd:-1_container:9f89600d11c0_pid:203736",
        "uuid": "fd:-1_container:9f89600d11c0_pid:203736"
      }
    },
    {
      "id": "proc:container:9f89600d11c0:pid:203736",
      "meta": {
        "container_id": "9f89600d11c0",
        "container_image": "deploy-vuln-app:",
        "name": "python",
        "pathname": "",
        "pid": 203736,
        "pod_name": null,
        "uuid": "container:9f89600d11c0:pid:203736"
      }
    }
  ]
}