{
  "edges": [
    {
      "bin_idx": 1,
      "count": 8,
      "dst": "proc:container:0a68610a418d:pid:167116",
      "event_name": "mmap",
      "event_names": [
        "mmap"
      ],
      "first_ts": 39832037976000,
      "last_ts": 39833809104000,
      "segments": [
        {
          "bin": 1,
          "count": 8
        }
      ],
      "src": "file:fd:-1_container:0a68610a418d_pid:167116",
      "type": "Mmap"
    },
    {
      "bin_idx": 2,
      "count": 6,
      "dst": "proc:container:0a68610a418d:pid:167116",
      "event_name": "mmap",
      "event_names": [
        "mmap"
      ],
      "first_ts": 39834593253000,
      "last_ts": 39835942111000,
      "segments": [
        {
          "bin": 2,
          "count": 6
        }
      ],
      "src": "file:fd:-1_container:0a68610a418d_pid:167116",
      "type": "Mmap"
    },
    {
      "bin_idx": 3,
      "count": 10,
      "dst": "proc:container:0a68610a418d:pid:167116",
      "event_name": "mmap",
      "event_names": [
        "mmap"
      ],
      "first_ts": 39836109030000,
      "last_ts": 39837736345000,
      "segments": [
        {
          "bin": 3,
          "count": 10
        }
      ],
      "src": "file:fd:-1_container:0a68610a418d_pid:167116",
      "type": "Mmap"
    },
    {
      "bin_idx": 4,
      "count": 8,
      "dst": "proc:container:0a68610a418d:pid:167116",
      "event_name": "mmap",
      "event_names": [
        "mmap"
      ],
      "first_ts": 39838577261000,
      "last_ts": 39839641897000,
      "segments": [
        {
          "bin": 4,
          "count": 8
        }
      ],
      "src": "file:fd:-1_container:0a68610a418d_pid:167116",
      "type": "Mmap"
    },
    {
      "bin_idx": 5,
      "count": 2,
      "dst": "proc:container:0a68610a418d:pid:167116",
      "event_name": "mmap",
      "event_names": [
        "mmap"
      ],
      "first_ts": 39840494736000,
      "last_ts": 39840494843000,
      "segments": [
        {
          "bin": 5,
          "count": 2
        }
      ],
      "src": "file:fd:-1_container:0a68610a418d_pid:167116",
      "type": "Mmap"
    },
    {
      "bin_idx": 6,
      "count": 10,
      "dst": "proc:container:0a68610a418d:pid:167116",
      "event_name": "mmap",
      "event_names": [
        "mmap"
      ],
      "first_ts": 39843032227000,
      "last_ts": 39843931980000,
      "segments": [
        {
          "bin": 6,
          "count": 10
        }
      ],
      "src": "file:fd:-1_container:0a68610a418d_pid:167116",
      "type": "Mmap"
    },
    {
      "bin_idx": 7,
      "count": 8,
      "dst": "proc:container:0a68610a418d:pid:167116",
      "event_name": "mmap",
      "event_names": [
        "mmap"
      ],
      "first_ts": 39844289345000,
      "last_ts": 39845182138000,
      "segments": [
        {
          "bin": 7,
          "count": 8
        }
      ],
      "src": "file:fd:-1_container:0a68610a418d_pid:167116",
      "type": "Mmap"
    },
    {
      "bin_idx": 8,
      "count": 12,
      "dst": "proc:container:0a68610a418d:pid:167116",
      "event_name": "mmap",
      "event_names": [
        "mmap"
      ],
      "first_ts": 39846114352000,
      "last_ts": 39847724016000,
      "segments": [
        {
          "bin": 8,
          "count": 12
        }
      ],
      "src": "file:fd:-1_container:0a68610a418d_pid:167116",
      "type": "Mmap"
    },
    {
      "bin_idx": 9,
      "count": 8,
      "dst": "proc:container:0a68610a418d:pid:167116",
      "event_name": "mmap",
      "event_names": [
        "mmap"
      ],
      "first_ts": 39848236860000,
      "last_ts": 39850034075000,
      "segments": [
        {
          "bin": 9,
          "count": 8
        }
      ],
      "src": "file:fd:-1_container:0a68610a418d_pid:167116",
      "type": "Mmap"
    },
    {
      "bin_idx": 10,
      "count": 2,
      "dst": "proc:container:0a68610a418d:pid:167116",
      "event_name": "mmap",
      "event_names": [
        "mmap"
      ],
      "first_ts": 39850417027000,
      "last_ts": 39850417142000,
      "segments": [
        {
          "bin": 10,
          "count": 2
        }
      ],
      "src": "file:fd:-1_container:0a68610a418d_pid:167116",
      "type": "Mmap"
    },
    {
      "bin_idx": 11,
      "count": 6,
      "dst": "proc:container:0a68610a418d:pid:167116",
      "event_name": "mmap",
      "event_names": [
        "mmap"
      ],
      "first_ts": 39852670889000,
      "last_ts": 39853520490000,
      "segments": [
        {
          "bin": 11,
          "count": 6
        }
      ],
      "src": "file:fd:-1_container:0a68610a418d_pid:167116",
      "type": "Mmap"
    },
    {
      "bin_idx": 12,
      "count": 18,
      "dst": "proc:container:0a68610a418d:pid:167116",
      "event_name": "mmap",
      "event_names": [
        "mmap"
      ],
      "first_ts": 39854297056000,
      "last_ts": 39856027105000,
      "segments": [
        {
          "bin": 12,
          "count": 18
        }
      ],
      "src": "file:fd:-1_container:0a68610a418d_pid:167116",
      "type": "Mmap"
    },
    {
      "bin_idx": 13,
      "count": 6,
      "dst": "proc:container:0a68610a418d:pid:167116",
      "event_name": "mmap",
      "event_names": [
        "mmap"
      ],
      "first_ts": 39856735486000,
      "last_ts": 39857516634000,
      "segments": [
        {
          "bin": 13,
          "count": 6
        }
      ],
      "src": "file:fd:-1_container:0a68610a418d_pid:167116",
      "type": "Mmap"
    },
    {
      "bin_idx": 14,
      "count": 4,
      "dst": "proc:container:0a68610a418d:pid:167116",
      "event_name": "mmap",
      "event_names": [
        "mmap"
      ],
      "first_ts": 39859418432000,
      "last_ts": 39859967719000,
      "segments": [
        {
          "bin": 14,
          "count": 4
        }
      ],
      "src": "file:fd:-1_container:0a68610a418d_pid:167116",
      "type": "Mmap"
    },
    {
      "bin_idx": 15,
      "count": 4,
      "dst": "proc:container:0a68610a418d:pid:167116",
      "event_name": "mmap",
      "event_names": [
        "mmap"
      ],
      "first_ts": 39861078021000,
      "last_ts": 39861284133000,
      "segments": [
        {
          "bin": 15,
          "count": 4
        }
      ],
      "src": "file:fd:-1_container:0a68610a418d_pid:167116",
      "type": "Mmap"
    }
  ],
  "metadata": {
    "reduction_config": {
      "edge_key_mode": "event_time_bin",
      "time_bin_seconds": 2,
      "window_seconds": 30
    }
  },
  "nodes": [
    {
      "id": "file:fd:-1_container:0a68610a418d_pid:167116",
      "meta": {
        "name": "fd:-1_container:0a68610a418d_pid:167116",
        "pathname": "fd:-1_container:0a68610a418d_pid:167116",
        "uuid": "fd:-1_container:0a68610a418d_pid:167116"
      }
    },
    {
      "id": "proc:container:0a68610a418d:pid:167116",
      "meta": {
        "container_id": "0a68610a418d",
        "container_image": "deploy-vuln-app:",
        "name": "python",
        "pathname": "",
        "pid": 167116,
        "pod_name": null,
        "uuid": "container:0a68610a418d:pid:167116"
      }
    }
  ]
}