{
  "edges": [
    {
      "bin_idx": 1,
      "count": 9,
      "dst": "proc:container:0a68610a418d:pid:167116",
      "event_name": "mmap",
      "event_names": [
        "mmap"
      ],
      "first_ts": 38140171630000,
      "last_ts": 38141172896000,
      "segments": [
        {
          "bin": 1,
          "count": 9
        }
      ],
      "src": "file:fd:-1_container:0a68610a418d_pid:167116",
      "type": "Mmap"
    },
    {
      "bin_idx": 2,
      "count": 9,
      "dst": "proc:container:0a68610a418d:pid:167116",
      "event_name": "mmap",
      "event_names": [
        "mmap"
      ],
      "first_ts": 38143284339000,
      "last_ts": 38144016609000,
      "segments": [
        {
          "bin": 2,
          "count": 9
        }
      ],
      "src": "file:fd:-1_container:0a68610a418d_pid:167116",
      "type": "Mmap"
    },
    {
      "bin_idx": 3,
      "count": 3,
      "dst": "proc:container:0a68610a418d:pid:167116",
      "event_name": "mmap",
      "event_names": [
        "mmap"
      ],
      "first_ts": 38144277067000,
      "last_ts": 38144277163000,
      "segments": [
        {
          "bin": 3,
          "count": 3
        }
      ],
      "src": "file:fd:-1_container:0a68610a418d_pid:167116",
      "type": "Mmap"
    },
    {
      "bin_idx": 4,
      "count": 15,
      "dst": "proc:container:0a68610a418d:pid:167116",
      "event_name": "mmap",
      "event_names": [
        "mmap"
      ],
      "first_ts": 38146892427000,
      "last_ts": 38147879094000,
      "segments": [
        {
          "bin": 4,
          "count": 15
        }
      ],
      "src": "file:fd:-1_container:0a68610a418d_pid:167116",
      "type": "Mmap"
    },
    {
      "bin_idx": 5,
      "count": 9,
      "dst": "proc:container:0a68610a418d:pid:167116",
      "event_name": "mmap",
      "event_names": [
        "mmap"
      ],
      "first_ts": 38148912968000,
      "last_ts": 38150049813000,
      "segments": [
        {
          "bin": 5,
          "count": 9
        }
      ],
      "src": "file:fd:-1_container:0a68610a418d_pid:167116",
      "type": "Mmap"
    },
    {
      "bin_idx": 6,
      "count": 11,
      "dst": "proc:container:0a68610a418d:pid:167116",
      "event_name": "mmap",
      "event_names": [
        "mmap"
      ],
      "first_ts": 38150518442000,
      "last_ts": 38152068250000,
      "segments": [
        {
          "bin": 6,
          "count": 11
        }
      ],
      "src": "file:fd:-1_container:0a68610a418d_pid:167116",
      "type": "Mmap"
    },
    {
      "bin_idx": 7,
      "count": 2,
      "dst": "proc:container:0a68610a418d:pid:167116",
      "event_name": "mmap",
      "event_names": [
        "mmap"
      ],
      "first_ts": 38153461621000,
      "last_ts": 38153461755000,
      "segments": [
        {
          "bin": 7,
          "count": 2
        }
      ],
      "src": "file:fd:-1_container:0a68610a418d_pid:167116",
      "type": "Mmap"
    },
    {
      "bin_idx": 8,
      "count": 4,
      "dst": "proc:container:0a68610a418d:pid:167116",
      "event_name": "mmap",
      "event_names": [
        "mmap"
      ],
      "first_ts": 38154476588000,
      "last_ts": 38154575546000,
      "segments": [
        {
          "bin": 8,
          "count": 4
        }
      ],
      "src": "file:fd:-1_container:0a68610a418d_pid:167116",
      "type": "Mmap"
    },
    {
      "bin_idx": 9,
      "count": 8,
      "dst": "proc:container:0a68610a418d:pid:167116",
      "event_name": "mmap",
      "event_names": [
        "mmap"
      ],
      "first_ts": 38156374811000,
      "last_ts": 38158048870000,
      "segments": [
        {
          "bin": 9,
          "count": 8
        }
      ],
      "src": "file:fd:-1_container:0a68610a418d_pid:167116",
      "type": "Mmap"
    },
    {
      "bin_idx": 10,
      "count": 2,
      "dst": "proc:container:0a68610a418d:pid:167116",
      "event_name": "mmap",
      "event_names": [
        "mmap"
      ],
      "first_ts": 38158239238000,
      "last_ts": 38158239343000,
      "segments": [
        {
          "bin": 10,
          "count": 2
        }
      ],
      "src": "file:fd:-1_container:0a68610a418d_pid:167116",
      "type": "Mmap"
    },
    {
      "bin_idx": 11,
      "count": 4,
      "dst": "proc:container:0a68610a418d:pid:167116",
      "event_name": "mmap",
      "event_names": [
        "mmap"
      ],
      "first_ts": 38160471307000,
      "last_ts": 38161892626000,
      "segments": [
        {
          "bin": 11,
          "count": 4
        }
      ],
      "src": "file:fd:-1_container:0a68610a418d_pid:167116",
      "type": "Mmap"
    },
    {
      "bin_idx": 12,
      "count": 8,
      "dst": "proc:container:0a68610a418d:pid:167116",
      "event_name": "mmap",
      "event_names": [
        "mmap"
      ],
      "first_ts": 38162353858000,
      "last_ts": 38163267830000,
      "segments": [
        {
          "bin": 12,
          "count": 8
        }
      ],
      "src": "file:fd:-1_container:0a68610a418d_pid:167116",
      "type": "Mmap"
    },
    {
      "bin_idx": 14,
      "count": 6,
      "dst": "proc:container:0a68610a418d:pid:167116",
      "event_name": "mmap",
      "event_names": [
        "mmap"
      ],
      "first_ts": 38166343120000,
      "last_ts": 38168039115000,
      "segments": [
        {
          "bin": 14,
          "count": 6
        }
      ],
      "src": "file:fd:-1_container:0a68610a418d_pid:167116",
      "type": "Mmap"
    },
    {
      "bin_idx": 15,
      "count": 6,
      "dst": "proc:container:0a68610a418d:pid:167116",
      "event_name": "mmap",
      "event_names": [
        "mmap"
      ],
      "first_ts": 38168181953000,
      "last_ts": 38169915255000,
      "segments": [
        {
          "bin": 15,
          "count": 6
        }
      ],
      "src": "file:fd:-1_container:0a68610a418d_pid:167116",
      "type": "Mmap"
    }
  ],
  "metadata": {
    "reduction_config": {
      "edge_key_mode": "event_time_bin",
      "time_bin_seconds": 2,
      "window_seconds": 30
    }
  },
  "nodes": [
    {
      "id": "file:fd:-1_container:0a68610a418d_pid:167116",
      "meta": {
        "name": "fd:-1_container:0a68610a418d_pid:167116",
        "pathname": "fd:-1_container:0a68610a418d_pid:167116",
        "uuid": "fd:-1_container:0a68610a418d_pid:167116"
      }
    },
    {
      "id": "proc:container:0a68610a418d:pid:167116",
      "meta": {
        "container_id": "0a68610a418d",
        "container_image": "deploy-vuln-app:",
        "name": "python",
        "pathname": "",
        "pid": 167116,
        "pod_name": null,
        "uuid": "container:0a68610a418d:pid:167116"
      }
    }
  ]
}