{
  "edges": [
    {
      "bin_idx": 1,
      "count": 12,
      "dst": "proc:container:0a68610a418d:pid:167116",
      "event_name": "mmap",
      "event_names": [
        "mmap"
      ],
      "first_ts": 36642857670000,
      "last_ts": 36644684898000,
      "segments": [
        {
          "bin": 1,
          "count": 12
        }
      ],
      "src": "file:fd:-1_container:0a68610a418d_pid:167116",
      "type": "Mmap"
    },
    {
      "bin_idx": 2,
      "count": 3,
      "dst": "proc:container:0a68610a418d:pid:167116",
      "event_name": "mmap",
      "event_names": [
        "mmap"
      ],
      "first_ts": 36646233345000,
      "last_ts": 36646233446000,
      "segments": [
        {
          "bin": 2,
          "count": 3
        }
      ],
      "src": "file:fd:-1_container:0a68610a418d_pid:167116",
      "type": "Mmap"
    },
    {
      "bin_idx": 3,
      "count": 9,
      "dst": "proc:container:0a68610a418d:pid:167116",
      "event_name": "mmap",
      "event_names": [
        "mmap"
      ],
      "first_ts": 36646989748000,
      "last_ts": 36648197080000,
      "segments": [
        {
          "bin": 3,
          "count": 9
        }
      ],
      "src": "file:fd:-1_container:0a68610a418d_pid:167116",
      "type": "Mmap"
    },
    {
      "bin_idx": 4,
      "count": 15,
      "dst": "proc:container:0a68610a418d:pid:167116",
      "event_name": "mmap",
      "event_names": [
        "mmap"
      ],
      "first_ts": 36649699747000,
      "last_ts": 36650456577000,
      "segments": [
        {
          "bin": 4,
          "count": 15
        }
      ],
      "src": "file:fd:-1_container:0a68610a418d_pid:167116",
      "type": "Mmap"
    },
    {
      "bin_idx": 5,
      "count": 3,
      "dst": "proc:container:0a68610a418d:pid:167116",
      "event_name": "mmap",
      "event_names": [
        "mmap"
      ],
      "first_ts": 36652818758000,
      "last_ts": 36652818907000,
      "segments": [
        {
          "bin": 5,
          "count": 3
        }
      ],
      "src": "file:fd:-1_container:0a68610a418d_pid:167116",
      "type": "Mmap"
    },
    {
      "bin_idx": 6,
      "count": 9,
      "dst": "proc:container:0a68610a418d:pid:167116",
      "event_name": "mmap",
      "event_names": [
        "mmap"
      ],
      "first_ts": 36654637657000,
      "last_ts": 36654810152000,
      "segments": [
        {
          "bin": 6,
          "count": 9
        }
      ],
      "src": "file:fd:-1_container:0a68610a418d_pid:167116",
      "type": "Mmap"
    },
    {
      "bin_idx": 7,
      "count": 9,
      "dst": "proc:container:0a68610a418d:pid:167116",
      "event_name": "mmap",
      "event_names": [
        "mmap"
      ],
      "first_ts": 36654947552000,
      "last_ts": 36655928469000,
      "segments": [
        {
          "bin": 7,
          "count": 9
        }
      ],
      "src": "file:fd:-1_container:0a68610a418d_pid:167116",
      "type": "Mmap"
    },
    {
      "bin_idx": 8,
      "count": 12,
      "dst": "proc:container:0a68610a418d:pid:167116",
      "event_name": "mmap",
      "event_names": [
        "mmap"
      ],
      "first_ts": 36657133860000,
      "last_ts": 36657886290000,
      "segments": [
        {
          "bin": 8,
          "count": 12
        }
      ],
      "src": "file:fd:-1_container:0a68610a418d_pid:167116",
      "type": "Mmap"
    },
    {
      "bin_idx": 9,
      "count": 12,
      "dst": "proc:container:0a68610a418d:pid:167116",
      "event_name": "mmap",
      "event_names": [
        "mmap"
      ],
      "first_ts": 36659100345000,
      "last_ts": 36660853853000,
      "segments": [
        {
          "bin": 9,
          "count": 12
        }
      ],
      "src": "file:fd:-1_container:0a68610a418d_pid:167116",
      "type": "Mmap"
    },
    {
      "bin_idx": 10,
      "count": 12,
      "dst": "proc:container:0a68610a418d:pid:167116",
      "event_name": "mmap",
      "event_names": [
        "mmap"
      ],
      "first_ts": 36662252026000,
      "last_ts": 36662678064000,
      "segments": [
        {
          "bin": 10,
          "count": 12
        }
      ],
      "src": "file:fd:-1_container:0a68610a418d_pid:167116",
      "type": "Mmap"
    },
    {
      "bin_idx": 11,
      "count": 3,
      "dst": "proc:container:0a68610a418d:pid:167116",
      "event_name": "mmap",
      "event_names": [
        "mmap"
      ],
      "first_ts": 36664173588000,
      "last_ts": 36664173683000,
      "segments": [
        {
          "bin": 11,
          "count": 3
        }
      ],
      "src": "file:fd:-1_container:0a68610a418d_pid:167116",
      "type": "Mmap"
    },
    {
      "bin_idx": 12,
      "count": 12,
      "dst": "proc:container:0a68610a418d:pid:167116",
      "event_name": "mmap",
      "event_names": [
        "mmap"
      ],
      "first_ts": 36664879702000,
      "last_ts": 36666262649000,
      "segments": [
        {
          "bin": 12,
          "count": 12
        }
      ],
      "src": "file:fd:-1_container:0a68610a418d_pid:167116",
      "type": "Mmap"
    },
    {
      "bin_idx": 13,
      "count": 3,
      "dst": "proc:container:0a68610a418d:pid:167116",
      "event_name": "mmap",
      "event_names": [
        "mmap"
      ],
      "first_ts": 36667552772000,
      "last_ts": 36667552876000,
      "segments": [
        {
          "bin": 13,
          "count": 3
        }
      ],
      "src": "file:fd:-1_container:0a68610a418d_pid:167116",
      "type": "Mmap"
    },
    {
      "bin_idx": 14,
      "count": 9,
      "dst": "proc:container:0a68610a418d:pid:167116",
      "event_name": "mmap",
      "event_names": [
        "mmap"
      ],
      "first_ts": 36669957050000,
      "last_ts": 36670755339000,
      "segments": [
        {
          "bin": 14,
          "count": 9
        }
      ],
      "src": "file:fd:-1_container:0a68610a418d_pid:167116",
      "type": "Mmap"
    },
    {
      "bin_idx": 15,
      "count": 6,
      "dst": "proc:container:0a68610a418d:pid:167116",
      "event_name": "mmap",
      "event_names": [
        "mmap"
      ],
      "first_ts": 36672621741000,
      "last_ts": 36672734045000,
      "segments": [
        {
          "bin": 15,
          "count": 6
        }
      ],
      "src": "file:fd:-1_container:0a68610a418d_pid:167116",
      "type": "Mmap"
    }
  ],
  "metadata": {
    "reduction_config": {
      "edge_key_mode": "event_time_bin",
      "time_bin_seconds": 2,
      "window_seconds": 30
    }
  },
  "nodes": [
    {
      "id": "file:fd:-1_container:0a68610a418d_pid:167116",
      "meta": {
        "name": "fd:-1_container:0a68610a418d_pid:167116",
        "pathname": "fd:-1_container:0a68610a418d_pid:167116",
        "uuid": "fd:-1_container:0a68610a418d_pid:167116"
      }
    },
    {
      "id": "proc:container:0a68610a418d:pid:167116",
      "meta": {
        "container_id": "0a68610a418d",
        "container_image": "deploy-vuln-app:",
        "name": "python",
        "pathname": "",
        "pid": 167116,
        "pod_name": null,
        "uuid": "container:0a68610a418d:pid:167116"
      }
    }
  ]
}